LICENSE
MANIFEST.in
README.rst
setup.py
tailhead/__init__.py
tailhead/__main__.py
tailhead/version.py
tailhead.egg-info/PKG-INFO
tailhead.egg-info/SOURCES.txt
tailhead.egg-info/dependency_links.txt
tailhead.egg-info/entry_points.txt
tailhead.egg-info/top_level.txt