Metadata-Version: 1.1
Name: tailhead
Version: 1.0.1
Summary: tailhead is a simple implementation of GNU tail and head.
Home-page: https://github.com/GreatFruitOmsk/tailhead
Author: Ilya Kulakov
Author-email: kulakov.ilya@gmail.com
License: MIT
Download-URL: https://github.com/GreatFruitOmsk/tailhead/releases
Keywords: tail,head
Platform: UNKNOWN
Classifier: Programming Language :: Python
Classifier: Environment :: Console
Classifier: Intended Audience :: Developers
Classifier: Intended Audience :: System Administrators
Classifier: Operating System :: POSIX
Classifier: License :: OSI Approved :: MIT License
Classifier: Natural Language :: English
Classifier: Topic :: System :: Logging
Classifier: Topic :: Text Processing
Classifier: Topic :: Software Development :: Libraries :: Python Modules
Classifier: Topic :: System :: System Shells
Classifier: Topic :: System :: Systems Administration
Classifier: Programming Language :: Python :: 2.6
Classifier: Programming Language :: Python :: 2.7
Classifier: Programming Language :: Python :: 3.3
Classifier: Programming Language :: Python :: 3.4
